[
  {
    "id": 1,
    "title": "TWEES - திட்டம்",
    "category": "தமிழ்நாட்டுச் செய்திகள்",
    "date": "",
    "description": "தமிழ்நாடு மகளிர் தொழில்முனைவோர் அதிகாரமளிப்புத் திட்டம் (TWEES) தமிழ்நாட்டின்\nமுதல்வர் அவர்களால் தொடங்கப்பட்டது. அடுத்த ஐந்து ஆண்டுகளில் 1 லட்சம் பெண்கள் தொழில்முனைவோராக மாற ஊக்குவிப்பதை இந்தத்\nதிட்டம் நோக்கமாகக் கொண்டுள்ளது. இது தமிழ்நாடு குறு, சிறு மற்றும் நடுத்தர நிறுவனங்கள் (MSME) துறையால்\nசெயல்படுத்தப் படுகிறது. இந்தத் திட்டம் பெண் தொழில்முனைவோருக்கு பயிற்சி, நிதி உதவி மற்றும் நிறுவன ஆதரவை\nவழங்கும். இந்தத் திட்டம் MSME துறையில் பெண்களின் பங்களிப்பை அதிகரிப்பதையும், மாநிலத்தில்\nஅதிக வேலை வாய்ப்புகளை உருவாக்குவதையும் நோக்கமாகக் கொண்டுள்ளது."
  },
  {
    "id": 2,
    "title": "அழகு சாதன மையங்களுக்கான விதிகள்",
    "category": "தமிழ்நாட்டுச் செய்திகள்",
    "date": "",
    "description": "மாநிலத்தில் அழகு சாதனவியல், அழகியல் மற்றும் முடி மாற்று மையங்களை\nஒழுங்குபடுத்துவதற்கான அரசு உத்தரவை (G.O.) தமிழ்நாடு அரசு வெளியிட்டது. அத்தகைய அனைத்து மையங்களும் அவற்றின் செயல்பாட்டிற்காக தமிழ்நாடு மருத்துவ\nநிறுவனங்கள் சட்டத்தின் கீழ் பதிவு செய்ய வேண்டும். இந்த உத்தரவு தேசிய மருத்துவ ஆணையம் (NMC) வழங்கிய வழிகாட்டுதல்களை அடிப்படையாகக்\nகொண்டது. முடி மாற்று அறுவை சிகிச்சை மற்றும் அழகியல் நடைமுறைகளை தகுதிவாய்ந்த தோல்\nமருத்துவர்கள் அல்லது ஒட்டுறுப்பு அறுவை சிகிச்சை நிபுணர்களால் மட்டுமே மேற்கொள்ள\nமுடியும். தமிழ்நாடு தனியார் மருத்துவ நிறுவனங்கள் (ஒழுங்குமுறை) சட்டம், 1997 மாநிலத்தில்\nஉள்ள தனியார் மருத்துவ நிறுவனங்களை ஒழுங்குபடுத்துகிறது."
  },
  {
    "id": 3,
    "title": "மக்கள் தொகை கணக்கெடுப்பு 2027 உருவச்சின்னங்கள்",
    "category": "தேசியச் செய்திகள்",
    "date": "",
    "description": "பொது விழிப்புணர்வையும் பங்கேற்பையும் அதிகரிக்க இந்திய அரசு 2027 ஆம் ஆண்டு மக்கள்\nதொகை கணக்கெடுப்புக்காக பிரகதி மற்றும் விகாஸ் என்ற சின்னங்களை அறிமுகப்படுத்தியது. பிரகதி ஒரு பெண் கணக்கெடுப்பாளரையும், விகாஸ் ஒரு ஆண் கணக்கெடுப்பாளரையும்\nபிரதிநிதித்துவப்படுத்தும். தேசத்தைக் கட்டியெழுப்புவதில் பெண்கள் மற்றும் ஆண்களின் சமப் பங்களிப்பை இந்த\nஉருவச்சின்னங்கள் குறிக்கின்றன. மக்கள் தொகை கணக்கெடுப்பு 2027 என்பது அலைபேசிப் பயன்பாடுகள் மற்றும் தரவு\nசேகரிப்புக்கான டிஜிட்டல் தளங்களைப் பயன்படுத்தி இந்தியாவின் முதல் முழுமையான\nடிஜிட்டல் கணக்கெடுப்பாகும். மக்கள் தொகை கணக்கெடுப்பானது HLO (வீட்டுப் பட்டியல் மற்றும் வீட்டுவசதிக்\nகணக்கெடுப்பு) மற்றும் PE (மக்கள் தொகை கணக்கெடுப்பு) என இரண்டு கட்டங்களாக\nநடத்தப்படும்."
  },
  {
    "id": 4,
    "title": "நிதி ஆயோக் - யுனிசெஃப் கூட்டாண்மை",
    "category": "தேசியச் செய்திகள்",
    "date": "",
    "description": "நிதி ஆயோக் மற்றும் யுனிசெஃப் இந்தியா ஆகியவை இலட்சிய மாவட்டங்கள் மற்றும்\nஇலட்சியத் தொகுதிகளில் ஊட்டச்சத்து மற்றும் சுகாதார விளைவுகளை மேம்படுத்துவதற்கான\nநோக்க அறிக்கை (SOI) ஒன்றில் கையெழுத்திட்டன. இந்தக் கூட்டாண்மை பின்தங்கிய பகுதிகளில் தாய் மற்றும் குழந்தை ஊட்டச்சத்து\nசேவைகளில் கவனம் செலுத்துகிறது. IMPAct4Nutrition (I4N) தளம் ஊட்டச்சத்து திட்டங்களுக்கான பெருநிறுவன சமூக பொறுப்பு\n(CSR) நிதிகளைத் திரட்டும். இந்த முன்னெடுப்பு இலட்சிய மாவட்டங்களில் ஊட்டச்சத்து திட்டங்களைச் செயல்\nபடுத்துவதையும் கண்காணிப்பதையும் மேம்படுத்துவதை நோக்கமாகக் கொண்டு உள்ளது."
  },
  {
    "id": 5,
    "title": "குழந்தைகளுக்கான சமூக ஊடகக் கட்டுப்பாடு - இந்தோனேசியா",
    "category": "சர்வதேசச் செய்திகள்",
    "date": "",
    "description": "புதிய விதிமுறை மூலம் 16 வயதுக்குட்பட்ட குழந்தைகளுக்கான சமூக ஊடக அணுகலுக்கான\nகட்டுப்பாடுகளை இந்தோனேசியா அறிவித்துள்ளது. சிறார்களுக்கான இணைய மிரட்டல், அடிமையாதல் மற்றும் இணையதள அபாயங்களைக் குறைக்க இந்த\nவிதி பிறப்பிக்கப்பட்டது. டிக்டாக், பேஸ்புக், இன்ஸ்டாகிராம் மற்றும் ரோப்லாக்ஸ் போன்ற தளங்களில் 16\nவயதுக்குட்பட்ட குழந்தைகளின் கணக்குகள் மார்ச் 28, 2026 முதல் படிப்படியாக\nமுடக்கப்படும். ஆஸ்திரேலியா மற்றும் ஸ்பெயின் போன்ற நாடுகளும் சிறார்களுக்கு இதே போன்ற\nகட்டுப்பாடுகளை அறிமுகப்படுத்தியுள்ளன. மலேசியா 2026 ஆம் ஆண்டு முதல் 16 வயதுக்குட்பட்ட பயனர்களுக்கு சமூக ஊடகத் தடையை\nஅறிவித்துள்ளது."
  },
  {
    "id": 6,
    "title": "சுதர்சன் AI அமைப்பு",
    "category": "பொருளாதாரச் செய்திகள்",
    "date": "",
    "description": "சமூக ஊடகங்களில் நிதி நுந்துநர்களால் (Influencer) வெளியிடப்பட்ட 1.2\nலட்சத்திற்கும் அதிகமான தவறாக வழிநடத்தும் பதிவுகளை நீக்குவதற்கு, SEBI 'சுதர்சன்'\nஎன்ற செயற்கை நுண்ணறிவு (AI) அமைப்பைப் பயன்படுத்தியது. சுதர்சன் AI அமைப்பு என்பது இந்தியாவில் வங்கி மற்றும் நிதித் துறையில்\nபயன்படுத்தப்படும் ஒரு செயற்கை நுண்ணறிவு (AI) அடிப்படையிலான முடிவெடுக்கும் ஆதரவு\nஅமைப்பாகும். இது பெரிய நிதி தரவுத்தொகுப்புகளைச் செயலாக்குவதற்கும் முன்கணிப்பு நுண்ணறிவுகளை\nஉருவாக்குவதற்கும் இயந்திர கற்றல் மற்றும் தரவு பகுப்பாய்வுகளைப் பயன்படுத்துகிறது. இந்த அமைப்பு வங்கிகளுக்கு கடன் ஆபத்து மதிப்பீடு, கடன் மதிப்பீடு மற்றும் வாராக்\nகடன்களை முன்கூட்டியே எச்சரிக்கை செய்வதில் உதவுகிறது. இது நிதி நிறுவனங்களில் மோசடி கண்டறிதல், பரிவர்த்தனை கண்காணிப்பு மற்றும்\nஒழுங்குமுறை இணக்கத்திற்கும் பயன்படுத்தப்படுகிறது."
  },
  {
    "id": 7,
    "title": "Moonshot திட்டம்",
    "category": "அறிவியல் மற்றும் தொழில்நுட்பச் செய்திகள்",
    "date": "",
    "description": "Moonshot திட்டம் இந்திய அறிவியல் கழகத்தால் (IISc) தொடங்கப்பட்டது. இந்தத் திட்டம் நியூரோமார்பிக் வன்பொருள் மற்றும் செயற்கை நுண்ணறிவு (AI)\nநெறிமுறைகளை இணைக்கும் மூளை இணை செயலிகளை உருவாக்குவதை நோக்கமாகக் கொண்டுள்ளது. Brain co-processors என்பவை மூளையின் வெவ்வேறு பகுதிகளுடன் இணைப்பதன் மூலம்\nமூளையின் செயல்பாடுகளை மேம்படுத்த அல்லது மீட்டெடுக்க வடிவமைக்கப்பட்ட சாதனங்கள்\nஆகும். மென்மையான மற்றும் ஒருங்கிணைந்த இயக்கத்தை மீட்டெடுக்க, செயற்கை நுண்ணறிவு மூலம்\nஇயங்கும் குளோஸ்டு-லூப் (Closed-loop) சாதனத்தை இந்தத் திட்டம் உருவாக்கும். இந்தத் தொழில்நுட்பம் பக்கவாதத்தால் பாதிக்கப்பட்டவர்களுக்கு அறிவாற்றல் மறு வாழ்வு\nமற்றும் உணர்ச்சி இயக்கச் செயல்பாடுகளை மீட்டெடுக்க ஆதரவளிப்பதை நோக்கமாகக்\nகொண்டுள்ளது."
  },
  {
    "id": 8,
    "title": "விக்ரம் 1 - தனியார் ஏவுகலம்",
    "category": "அறிவியல் மற்றும் தொழில்நுட்பச் செய்திகள்",
    "date": "",
    "description": "ஸ்கைரூட் ஏரோஸ்பேஸ் (Skyroot Aerospace) நிறுவனம் இந்தியாவின் முதல் தனியார்\nசுற்றுப்பாதை ஏவுகலமான விக்ரம்-1 ஐ ஏவுவதற்குத் தயாராகி வருகிறது. இந்த ஏவுகலன் 300 கிலோ வரையிலான செயற்கைக்கோள்களை தாழ் புவிவட்ட சுற்றுப் பாதைக்கு\nகொண்டு செல்லும் வகையில் வடிவமைக்கப்பட்டுள்ளது என்ற நிலையில் இது\nஸ்ரீஹரிகோட்டாவில் உள்ள சதீஷ் தவான் விண்வெளி மையத்திலிருந்து ஏவப்படும். இந்திய விண்வெளித் திட்டத்தின் தந்தை விக்ரம் சாராபாய் அவர்களின் நினைவாக இந்த\nராக்கெட்டிற்குப் பெயரிடப்பட்டுள்ளது. முன்னதாக, இந்நிறுவனம் 2022 ஆம் ஆண்டில் இந்தியாவின் முதல் தனியார் துணை\nசுற்றுப்பாதை ஏவுகலமான விக்ரம்-S ஐ வெற்றிகரமாக ஏவியது."
  },
  {
    "id": 9,
    "title": "மெகாமாஸர் கண்டுபிடிப்பு",
    "category": "அறிவியல் மற்றும் தொழில்நுட்பச் செய்திகள்",
    "date": "",
    "description": "மீர்காட் (MeerKAT) ரேடியோ தொலைநோக்கி, பூமியிலிருந்து சுமார் 8 பில்லியன் ஒளி\nஆண்டுகள் தொலைவில் உள்ள ஒரு சக்திவாய்ந்த விண்வெளி \"கிகா லேசர்\" (ஹைட்ராக்சில்\nமெகாமாஸர்) ஒன்றைக் கண்டறிந்துள்ளது. மெகாமாஸர் என்பது தூண்டப்பட்ட கதிர்வீச்சு உமிழ்வு மூலம் நுண் அலைகள் அல்லது ரேடியோ\nஅலைகளைப் பெருக்கும் ஒரு இயற்கையான விண்வெளி மூலமாகும். விண்மீன் திரள்கள் மோதும் போதும் ஒன்றிணையும் போதும், தொலைதூர விண்மீன் திரளில்\nஉள்ள ஹைட்ராக்சில் (OH) மூலக்கூறுகளால் இந்த சமிக்ஞை உருவாக்கப் பட்டது. இந்த ரேடியோ சமிக்ஞை ஈர்ப்பு வில்லை மூலம் பெரிதாக்கப்பட்டது, இது ஒரு பெரிய\nவிண்மீன் திரள், ஒரு தொலைதூர மூலத்திலிருந்து வரும் ஒளியை வளைத்து பெருக்கும்\nநிகழ்வாகும். தென்னாப்பிரிக்காவில் அமைந்துள்ள மீர்காட் ரேடியோ தொலைநோக்கியானது ஸ்கொயர்\nகிலோமீட்டர் அரே (SKA) ரேடியோ வானியல் திட்டத்தின் ஒரு பகுதியாகும்."
  },
  {
    "id": 10,
    "title": "தேவாங்கு பாதுகாப்பு மையம்",
    "category": "சுற்றுச்சூழல் செய்திகள்",
    "date": "",
    "description": "இந்தியாவின் முதல் தேவாங்கு பாதுகாப்பு மையம் திண்டுக்கல் மாவட்டத்தில் திறந்து\nவைக்கப்பட்டது. இந்த மையம் தேவாங்குகளின் பாதுகாப்பு மற்றும் ஆராய்ச்சிப் பணிகளில் கவனம்\nசெலுத்துகிறது. தேவாங்கு என்பது தென்னிந்தியா மற்றும் இலங்கையின் வறண்ட காடுகள் மற்றும்\nபுதர்க்காடுகளில் காணப்படும் ஒரு சிறிய மரவாழ் பாலூட்டி இனம் ஆகும். முன்னதாக, தமிழ்நாடு அரசு கடவூர் தேவாங்கு சரணாலயத்தை அறிவித்திருந்தது. இந்தச் சரணாலயம் திண்டுக்கல் மற்றும் கரூர் மாவட்டங்களில் உள்ள ஏழு பிரிவுகளில்\n11,806.56 ஹெக்டேர் பரப்பளவைக் கொண்டுள்ளது. இதில் தோப்பசாமிமலை, தண்ணீர்க்கரடு, முடிமலை மற்றும் டி. இடையப்பட்டி போன்ற\nகாப்புக்காடுகள் அடங்கும்."
  },
  {
    "id": 11,
    "title": "இந்தியாவின் பல்லுயிர் முன்னேற்ற மதிப்பீடு",
    "category": "சுற்றுச்சூழல் செய்திகள்",
    "date": "",
    "description": "இந்தியா பல்லுயிர்ப் பெருக்க ஒப்பந்தத்தின் கீழான தனது 7வது தேசிய அறிக்கையை\nசமர்ப்பித்துள்ளது. இந்த அறிக்கை 23 தேசியப் பல்லுயிர் இலக்குகள் (NBTs) மற்றும் 142 குறிகாட்டிகளில்\nஇந்தியாவின் முன்னேற்றத்தை மதிப்பிடுகிறது. இந்த இலக்குகள் 2022 ஆம் ஆண்டு ஏற்றுக் கொள்ளப்பட்ட குன்மிங்-மாண்ட்ரியல்\nஉலகளாவியப் பல்லுயிர்க் கட்டமைப்புடன் (KMGBF) ஒத்துப்போகின்றன. இந்த அறிக்கையானது ஐக்கிய நாடுகள் வளர்ச்சித் திட்டத்தின் (UNDP) ஆதரவுடன் மத்திய\nசுற்றுச்சூழல், வனம் மற்றும் பருவநிலை மாற்ற அமைச்சகத்தால் (MoEFCC) தயாரிக்கப்\nபட்டது. தற்போது NBT1 – பல்லுயிர்த் திட்டமிடல் மற்றும் NBT2 – சூழலியல் மறுசீரமைப்பு ஆகிய\nஇரண்டு இலக்குகள் மட்டுமே சரியான பாதையில் உள்ளன. பல்லுயிர்ப்  பெருக்க ஒப்பந்தம் (CBD) என்பது பல்லுயிர்ப் பாதுகாப்பு மற்றும்\nநீடித்த பயன்பாட்டிற்காக 1992 ஆம் ஆண்டு ரியோ புவி உச்சி மாநாட்டில் ஏற்றுக்\nகொள்ளப் பட்ட ஒரு உலகளாவிய ஒப்பந்தமாகும்."
  },
  {
    "id": 12,
    "title": "பிரசவ ஊக்கத் திட்டம்",
    "category": "மாநிலச் செய்திகள்",
    "date": "",
    "description": "ஆந்திரப் பிரதேச மாநில அரசு இரண்டாவது அல்லது மூன்றாவது குழந்தையைப் பெறும்\nதம்பதிகளுக்கு ₹25,000 நிதி ஊக்கத்தொகையை அறிவித்தது. இந்தத் திட்டம் மாநிலத்தில் மொத்த கருவுறுதல் விகிதத்தை (TFR) அதிகரிப்பதை\nநோக்கமாகக் கொண்டுள்ளது. ஆந்திரப் பிரதேசத்தின் மொத்த கருவுறுதல் விகிதம் சுமார் 1.5 ஆகும் என்பதோடு இது 2.1\nஎன்ற மாற்று கருவுறுதல் அளவை விடக் குறைவாக உள்ளது. இந்தத் திட்டத்தின் கீழ், இரண்டாவது அல்லது மூன்றாவது குழந்தைக்கு பிரசவத்தின் போது\nதம்பதிகளுக்கு ₹25,000 வழங்கப்படும். இந்தக் கொள்கை மாநிலத்தில் குறைந்து வரும் பிறப்பு விகிதங்கள் மற்றும் அதிகரித்து\nவரும் வயதான மக்கள்தொகையை நிவர்த்தி செய்வதை நோக்கமாகக் கொண்டுள்ளது. உள்ளாட்சித் தேர்தல்களில் இரண்டு குழந்தைகள் விதிமுறை தொடர்பான விதிகளில்\nமாற்றங்களை அரசாங்கம் பரிசீலித்து வருகிறது."
  },
  {
    "id": 13,
    "title": "TNPSC துளிகள்",
    "category": "TNPSC துளிகள்",
    "date": "",
    "description": "ஆகாஷவானியின் கூடுதல் தலைமை இயக்குநர் தீரஜ் காகடியா எழுதிய “Mahatma: A Great\nCommunicator” என்ற புத்தகம் புது தில்லியில் வெளியிடப்பட்டது. அமெரிக்காவின் யெல்லோஸ்டோன் தேசியப் பூங்காவில் உள்ள எக்கினஸ்  வெந்நீரூற்றானது ஆறு\nஆண்டுகள் செயலற்ற நிலைக்குப் பிறகு மீண்டும் வெடித்தது.\n * உலகின் மிகப்பெரிய அமிலத்தன்மை கொண்ட  வெந்நீரூற்று ஆன இது யெல்லோஸ்டோனில் உள்ள\n   அதி புவிவெப்பப் பகுதியான நோரிஸ்  வெந்நீரூற்றுப் படுகையில் அமைந்துள்ளது. உலகின் மிகப்பெரிய அமிலத்தன்மை கொண்ட  வெந்நீரூற்று ஆன இது யெல்லோஸ்டோனில் உள்ள அதி\nபுவிவெப்பப் பகுதியான நோரிஸ்  வெந்நீரூற்றுப் படுகையில் அமைந்துள்ளது. 2026 ஆம் ஆண்டு மார்ச் 1 முதல் 5 ஆம் தேதி வரை ஜனஒளஷதி வாரம் 2026\nகொண்டாடப்படுவதையொட்டி,  இந்திய மருந்துகள் மற்றும் மருத்துவ உபகரணங்கள்\nவாரியத்தால் (PMBI) இந்தியா முழுவதும் மருத்துவ முகாம்கள் நடத்தப்படுகின்றன. அமெரிக்க உச்ச நீதிமன்றத்தின் தீர்ப்பைத் தொடர்ந்து, டொனால்ட் டிரம்பின்\nநிர்வாகத்தின் போது சட்டவிரோதமாக வசூலிக்கப்பட்ட சுமார் $130 பில்லியன்\nகட்டணங்களைத் திருப்பித் தருமாறு அமெரிக்க சர்வதேச வர்த்தக நீதிமன்றம்\nஅரசாங்கத்திற்கு உத்தரவிட்டது. அலைபேசி மற்றும் தொழில்நுட்பத் துறைக்கான உலகின் மிகப்பெரிய நிகழ்வான அலைபேசி உலக\nகாங்கிரஸ் 2026, ஸ்பெயினின் பார்சிலோனாவில் நடைபெறுகிறது.\n * 2026 ஆம் ஆண்டின் கருத்துரு \"The IQ Era\" ஆகும். 2026 ஆம் ஆண்டின் கருத்துரு \"The IQ Era\" ஆகும். கர்நாடக அரசு 2026–27 ஆம் ஆண்டிற்கான மாநில பட்ஜெட்டில் 16 வயதுக்குட்பட்ட\nகுழந்தைகளுக்கான சமூக ஊடக அணுகலைத் தடை செய்வதாக அறிவித்தது.\n * இந்தக் கட்டுப்பாடு பேஸ்புக், இன்ஸ்டாகிராம், ட்விட்டர் மற்றும் டிக்டாக் போன்ற\n   தளங்களுக்குப் பொருந்தும். இந்தக் கட்டுப்பாடு பேஸ்புக், இன்ஸ்டாகிராம், ட்விட்டர் மற்றும் டிக்டாக் போன்ற\nதளங்களுக்குப் பொருந்தும். உலகம் முழுவதும் பாலினச் சமத்துவம் மற்றும் பெண்கள் அதிகாரமளிப்பை\nமேம்படுத்துவதற்காக 2026 ஆம் ஆண்டு சர்வதேச மகளிர் தினம் மார்ச் 8 ஆம் தேதி உலகம்\nமுழுவதும் அனுசரிக்கப்படுகிறது.\n * 2026 ஆம் ஆண்டின் கருத்துரு \"Rights. Justice. Action. For ALL Women and Girls\"\n   என்பதாகும். 2026 ஆம் ஆண்டின் கருத்துரு \"Rights. Justice. Action. For ALL Women and Girls\"\nஎன்பதாகும்."
  },
  {
    "id": 14,
    "title": "புதிய திட்டங்கள் மற்றும் மேம்பாட்டுத் திட்டங்கள்",
    "category": "தமிழ்நாட்டுச் செய்திகள்",
    "date": "",
    "description": "தமிழ்நாட்டின் முதலமைச்சர் மு.க. ஸ்டாலின் சென்னையில் புதிய அரசுத் திட்டங்களைத்\nதொடங்கி வைத்தார் மற்றும் பல மேம்பாட்டுத் திட்டங்களைத் தொடங்கி வைத்தார். ஐந்து ஆண்டுகளில் சுமார் 1 லட்சம் பெண்கள் தொழில்முனைவோராக மாறுவதை\nஊக்குவிப்பதற்காக தமிழ்நாடு பெண்கள் தொழில்முனைவோர் அதிகாரமளிப்புத் திட்டம்\n(TWEES) குறு, சிறு மற்றும் நடுத்தர நிறுவனங்கள் (MSME) துறையால் தொடங்கப் பட்டது. நகர்ப்புற மேம்பாட்டிற்காக திருச்சிராப்பள்ளி முழுமைத் திட்டம் 2045 மற்றும்\nதூத்துக்குடி முழுமைத் திட்டம் 2045 ஆகியவற்றை அரசாங்கம் வெளியிட்டது. பிச்சாவரத்தில் சதுப்புநில பாதுகாப்பு மையம், மரக்காணத்தில் சர்வதேச இடம் பெயர்வு\nபறவை மையம் மற்றும் கோயம்புத்தூரில் நீலகிரி வரையாடு பாதுகாப்பு மையம்\nஆகியவற்றிற்கு அடிக்கல் நாட்டப்பட்டது. மருத்துவ வசதிகள் (₹167 கோடி), 60,000 மெட்ரிக் டன் திறன் கொண்ட கிடங்கு அலகுகள்\n(₹78 கோடி) மற்றும் மீன்வள உள்கட்டமைப்பு (₹100 கோடி) உள்ளிட்ட புதிய உள்\nகட்டமைப்புத் திட்டங்கள் தொடங்கப்பட்டன. டாக்டர் A.J.T. ஜான்சிங் வனவிலங்கு பாதுகாப்பு விருது மறைந்த கால்நடை மருத்துவர்\nவைத்தியநாதன் கிருஷ்ணமூர்த்தியின் மகனுக்கு வழங்கப்பட்டது. பெரியார்வாதி வி. ஆனைமுத்து மற்றும் எழுத்தாளர் ஈரோடு தமிழன்பன் ஆகியோரின்\nபடைப்புகளை தமிழக அரசு தேசியமயமாக்கியது என்பதோடு மேலும் காப்புரிமைத் தொகை\nஅவர்களின் குடும்ப உறுப்பினர்களிடம் ஒப்படைக்கப் பட்டது. மேலும் முதலமைச்சர் 500 அரிய ஆன்மீக புத்தகங்களையும், B.R. அம்பேத்கரின் 73\nபடைப்புகளின் தமிழ் மொழிபெயர்ப்புகளையும் வெளியிட்டார்."
  },
  {
    "id": 15,
    "title": "தமிழ்நாடு 2030: 14-அம்ச மேம்பாட்டு செயல்திட்டம்",
    "category": "தமிழ்நாட்டுச் செய்திகள்",
    "date": "",
    "description": "தமிழ்நாட்டின் முதலமைச்சர் மு.க. ஸ்டாலின் சென்னையில் 14-அம்ச துறை வாரியான\nசெயல்திட்டமான “தமிழ்நாடு 2030” ஐ வெளியிட்டார். “உங்க கனவ சொல்லுங்க” எனும் வீட்டுக் கணக்கெடுப்பு மூலம் 1.81 கோடி குடும்பங்களின்\nகருத்துகளின் அடிப்படையில் இந்த திட்டம் அமைந்துள்ளது. முன்னாள் குடியரசுத் தலைவர் A.P.J. அப்துல் கலாம் அவர்களால் ஈர்க்கப்பட்ட \"உத்தமர்\nகாந்தி மாதிரி கிராமங்கள் திட்டம்\", கிராமங்களைப் பொருளாதார வளர்ச்சியின் மையங்களாக\nமேம்படுத்துவதை நோக்கமாகக் கொண்டுள்ளது. இந்த திட்டம் 10 கிராமப் பஞ்சாயத்துகளுடன் தொடங்கி கிராமப்புறங்களில் நகர்ப்புற\nவசதிகளை வழங்கும். கலைஞர் கனவு இல்லம் திட்டத்தின் கீழ், கிராமப்புறங்களில் 5 லட்சம் வீடுகளும்,\nநகர்ப்புறங்களில் 2 லட்சம் வீடுகளும் கட்டப்படும். அனைவருக்கும் மருத்துவக் காப்பீடு உறுதி செய்யப்படுவதுடன் புற்று நோய், நீரிழிவு\nமற்றும் உயர் இரத்த அழுத்தத்தை முன்கூட்டியே கண்டறிவதற்கான சிறப்பு முகாம்கள்\nஏற்பாடு செய்யப்படும். தாய்மார்கள் இறப்பு விகிதம் (MMR) மற்றும் குழந்தை இறப்பு விகிதத்தை (IMR)\nகுறைப்பதில் இந்தியாவில் முதலிடத்தை அடைய மாநிலம் இலக்கு வைத்துள்ளது, மேலும்\nஒவ்வொரு மாவட்டத்திலும் மனநல ஆலோசனை மையங்கள் அமைக்கப் படும். விவசாயத்தில், நிகர விதைப்பு பரப்பளவு 50 லட்சம் ஹெக்டேராக அதிகரிக்கப்படுவதுடன்,\nமண் சுகாதார அட்டைகள் 43 லட்சம் விவசாயிகளுக்கு விநியோகிக்கப்படும். இயற்கை விவசாயம் சுமார் 17,000 ஹெக்டேராகவும், இயற்கை விவசாயம் 1 லட்சம்\nஹெக்டேராகவும், சொட்டு நீர்ப்பாசன வசதிகள் சுமார் 21 லட்சம் ஹெக்டேராகவும்\nவிரிவடையும். மேற்குத் தொடர்ச்சி மலைகள் மற்றும் கிழக்குத் தொடர்ச்சி மலைகளில் மழைநீர் சேகரிப்பு\nகட்டமைப்புகள் கட்டப்படும், மேலும் உணவு உற்பத்தி 125 லட்சம் மெட்ரிக் டன்னாக\nஅதிகரிக்கும். கல்வியில், இடைநிற்றல் நீக்கப்படுவதுடன் அனைத்து அரசு மற்றும் உதவி பெறும்\nபள்ளிகளிலும் 100% ஸ்மார்ட் வகுப்பறைகள் அறிமுகப்படுத்தப்படும். நூலகம் 5.0 இன் கீழ், 300க்கும் மேற்பட்ட நூலகங்கள் நிறுவப்படும், மேலும் 1,000\nமாதிரி பள்ளிகள் உருவாக்கப்படும். நான் முதல்வன் 2.0 திட்டம் உலகளாவியப் போட்டித் தன்மைக்காக மாணவர்களுக்கு மேம்பட்ட\nதிறன் பயிற்சி அளிக்கும். உயர்கல்வியில் மொத்த சேர்க்கை விகிதம் (GER) 90% ஆக அதிகரிக்கப்படும் மேலும்\nஆராய்ச்சிக்கான ஆய்வகங்கள், சிறப்பு மையங்கள் மற்றும் கல்வி நிறுவனங்களில் செயற்கை\nநுண்ணறிவு (AI) ஆய்வகங்கள் இருக்கும். விளையாட்டு வீரர்களுக்கான கல்விக் கடன்களுடன் கூடிய நெகிழ்வான பாடத் திட்டம்\nஅறிமுகப்படுத்தப்படும், மேலும் நிலமற்ற ஒவ்வொரு ஆதி திராவிடர் மற்றும் பழங்குடி\nகுடும்பத்திற்கும் படிப்படியாக வீட்டுப் பட்டா வழங்கப்படும். ₹18 லட்சம் கோடி முதலீட்டை ஈர்ப்பது, 50 லட்சம் இளைஞர்களுக்கு வேலைவாய்ப்பு\nஉருவாக்குவது, ஏற்றுமதியை $120 பில்லியனாக அதிகரிப்பது, “தமிழ்நாட்டில்\nதயாரிப்போம்” திட்டத்தின் கீழ் ஒவ்வொரு மாவட்டத்திலும் தொழில்துறை பூங்காக்களை\nநிறுவுவது, பாதசாரிகளுக்கு ஏற்ற சாலைகள், 20% பசுமையான இடங்கள், கழிவுநீர்\nமறுசுழற்சி வசதிகள் மற்றும் நவீன கலாச்சார மையங்களைக் கொண்ட நகரங்களை உருவாக்குவது\nஆகியவற்றையும் தமிழ்நாடு ஒரு நோக்கமாகக் கொண்டுள்ளது."
  }
]